<jqassistant-plugin xmlns="http://schema.jqassistant.org/plugin/v1.8"
                    xmlns:xsi="http://www.w3.org/2001/XMLSchema-instance"
                    xsi:schemaLocation="http://schema.jqassistant.org/plugin/v1.8 https://schema.jqassistant.org/plugin/jqassistant-plugin-v1.8.xsd"
                    name="Shared Rules">
    <description>Provides shared rules for my organization.</description>
    <rules>
        <resource>maven.xml</resource>
        <resource>package.xml</resource>
        <resource>my-organization.xml</resource>
    </rules>
</jqassistant-plugin>